teams_bot_ui/__init__.py
teams_bot_ui/cards/__init__.py
teams_bot_ui/cards/carousel_cards.py
teams_bot_ui/cards/chart_cards.py
teams_bot_ui/cards/copilot_cards.py
teams_bot_ui/cards/feature_cards.py
teams_bot_ui/cards/feedback_cards.py
teams_bot_ui/cards/file_cards.py
teams_bot_ui/cards/response_cards.py
teams_bot_ui/cards/session_cards.py
teams_bot_ui/cards/welcome_card.py
teams_bot_ui/cards/welcome_experience.py
teams_bot_ui/components/__init__.py
teams_bot_ui/components/buttons.py
teams_bot_ui/components/hero_elements.py
teams_bot_ui/components/list_components.py
teams_bot_ui/templates/__init__.py
teams_bot_ui/templates/card_templates.py
teams_bot_ui-1.0.0.dist-info/licenses/LICENSE
tests/__init__.py
tests/test_basic.py
teams_bot_ui-1.0.0.dist-info/METADATA
teams_bot_ui-1.0.0.dist-info/WHEEL
teams_bot_ui-1.0.0.dist-info/top_level.txt
teams_bot_ui-1.0.0.dist-info/RECORD
