Metadata-Version: 2.4
Name: teams-bot-ui
Version: 1.0.0
Summary: A comprehensive Python library for creating rich Microsoft Teams bot cards with Adaptive Cards support
Home-page: https://github.com/shubhamshinde7995/teams-bot-ui
Author: Shubham Shinde
Author-email: shubhamshinde7995@gmail.com
License: MIT
Project-URL: Bug Tracker, https://github.com/shubhamshinde7995/teams-bot-ui/issues
Project-URL: Documentation, https://github.com/shubhamshinde7995/teams-bot-ui#readme
Project-URL: Source, https://github.com/shubhamshinde7995/teams-bot-ui
Project-URL: Download, https://pypi.org/project/teams-bot-ui/
Keywords: microsoft teams,bot,adaptive cards,ui,chatbot,assistant,conversation,bot framework,teams bot,cards,interactive
Classifier: Development Status :: 4 - Beta
Classifier: Intended Audience :: Developers
Classifier: Topic :: Software Development :: Libraries :: Python Modules
Classifier: Topic :: Communications :: Chat
Classifier: Topic :: Internet :: WWW/HTTP :: Dynamic Content
Classifier: License :: OSI Approved :: MIT License
Classifier: Operating System :: OS Independent
Classifier: Programming Language :: Python :: 3
Classifier: Programming Language :: Python :: 3.8
Classifier: Programming Language :: Python :: 3.9
Classifier: Programming Language :: Python :: 3.10
Classifier: Programming Language :: Python :: 3.11
Classifier: Programming Language :: Python :: 3.12
Classifier: Topic :: Communications :: Conferencing
Classifier: Topic :: Software Development :: User Interfaces
Classifier: Environment :: Console
Classifier: Natural Language :: English
Requires-Python: >=3.8
License-File: LICENSE
Requires-Dist: botbuilder-core>=4.14.0
Provides-Extra: dev
Requires-Dist: pytest>=6.0; extra == "dev"
Requires-Dist: pytest-asyncio>=0.18.0; extra == "dev"
Requires-Dist: black>=22.0; extra == "dev"
Requires-Dist: mypy>=0.950; extra == "dev"
Requires-Dist: flake8>=4.0; extra == "dev"
Requires-Dist: twine>=4.0.0; extra == "dev"
Requires-Dist: build>=0.7.0; extra == "dev"
Provides-Extra: test
Requires-Dist: pytest>=6.0; extra == "test"
Requires-Dist: pytest-asyncio>=0.18.0; extra == "test"
Requires-Dist: pytest-cov>=3.0.0; extra == "test"
Dynamic: author
Dynamic: author-email
Dynamic: classifier
Dynamic: description
Dynamic: description-content-type
Dynamic: home-page
Dynamic: keywords
Dynamic: license
Dynamic: license-file
Dynamic: project-url
Dynamic: provides-extra
Dynamic: requires-dist
Dynamic: requires-python
Dynamic: summary
